github_utility/__init__.py
github_utility/cli.py
github_utility/github.py
github_utility-1.0.0.dist-info/LICENSE
github_utility-1.0.0.dist-info/METADATA
github_utility-1.0.0.dist-info/WHEEL
github_utility-1.0.0.dist-info/entry_points.txt
github_utility-1.0.0.dist-info/RECORD
