Metadata-Version: 2.1
Name: github-utility
Version: 1.0.0
Summary: A simple Python package for interacting with the GitHub API.
Author: Shivam Patil
Author-email: sbpatil5606@gmail.com
Requires-Python: >=3.8,<4.0
Classifier: Programming Language :: Python :: 3
Classifier: Programming Language :: Python :: 3.8
Classifier: Programming Language :: Python :: 3.9
Classifier: Programming Language :: Python :: 3.10
Classifier: Programming Language :: Python :: 3.11
Classifier: Programming Language :: Python :: 3.12
Requires-Dist: requests (>=2.32.3,<3.0.0)
